mercs/__init__.py
mercs/algo/__init__.py
mercs/algo/evaluation.py
mercs/algo/imputation.py
mercs/algo/induction.py
mercs/algo/inference.py
mercs/algo/inference_legacy.py
mercs/algo/prediction.py
mercs/algo/selection.py
mercs/composition/CanonicalModel.py
mercs/composition/CompositeModel.py
mercs/composition/__init__.py
mercs/composition/compose.py
mercs/core/Mercs.py
mercs/core/__init__.py
mercs/graph/__init__.py
mercs/graph/q_diagram.py
mercs/utils/__init__.py
mercs/utils/data/iris-test.csv
mercs/utils/data/iris-train.csv
mercs/utils/data_handling.py
mercs/utils/debug.py
mercs/utils/decoration.py
mercs/utils/encoding.py
mercs/utils/graphviz.py
mercs/utils/inference_tools.py
mercs/utils/inference_tools_legacy.py
mercs/utils/test_data.py
mercs/visuals/__init__.py
mercs/visuals/diagrams.py
mercs_mixed-0.0.45.dist-info/LICENSE.txt
mercs_mixed-0.0.45.dist-info/WHEEL
mercs_mixed-0.0.45.dist-info/METADATA
mercs_mixed-0.0.45.dist-info/RECORD
