Metadata-Version: 2.1
Name: mercs-mixed
Version: 0.0.45
Summary: MERCS: Multi-Directional Ensembles of Regression and Classification treeS
Home-page: https://github.com/systemallica/mercs
License: MIT
Author: Andrés Reverón Molina
Author-email: andres@reveronmolina.me
Requires-Python: >=3.8.0,<4.0.0
Classifier: Development Status :: 3 - Alpha
Classifier: License :: OSI Approved :: MIT License
Classifier: Programming Language :: Python :: 3
Classifier: Programming Language :: Python :: 3.8
Classifier: Topic :: Scientific/Engineering :: Artificial Intelligence
Classifier: Topic :: Software Development :: Libraries :: Python Modules
Requires-Dist: catboost (>=0.24,<0.25)
Requires-Dist: dask[delayed] (>=2.23.0,<3.0.0)
Requires-Dist: decision-tree-morfist (>=0.3.3,<0.4.0)
Requires-Dist: ipython (>=7.17.0,<8.0.0)
Requires-Dist: joblib (>=0.16.0,<0.17.0)
Requires-Dist: lightgbm (>=2.3.1,<3.0.0)
Requires-Dist: networkx (>=2.4,<3.0)
Requires-Dist: numpy (>=1.19.1,<2.0.0)
Requires-Dist: pydot (>=1.4.1,<2.0.0)
Requires-Dist: scikit-learn (>=0.23.2,<0.24.0)
Requires-Dist: shap (>=0.35.0,<0.36.0)
Project-URL: Repository, https://github.com/systemallica/mercs
